poaurk/__init__.py
poaurk/comet.py
poaurk/oauth.py
poaurk-0.6.0.dist-info/licenses/LICENSE
poaurk-0.6.0.dist-info/METADATA
poaurk-0.6.0.dist-info/WHEEL
poaurk-0.6.0.dist-info/top_level.txt
poaurk-0.6.0.dist-info/RECORD
