Metadata-Version: 2.4
Name: poaurk
Version: 0.6.0
Summary: Light Plurk API 2.0 Oauth Library
Author-email: Dephilia <me@dephilia.moe>
Requires-Python: >=3.10
License-File: LICENSE
Requires-Dist: aiofiles>=24.1.0
Requires-Dist: aiohttp>=3.9.3
Requires-Dist: oauthlib>=3.2.2
Dynamic: license-file
